findimage/__init__.py
findimage-0.2.0.dist-info/LICENSE
findimage-0.2.0.dist-info/METADATA
findimage-0.2.0.dist-info/WHEEL
findimage-0.2.0.dist-info/top_level.txt
findimage-0.2.0.dist-info/RECORD
