Metadata-Version: 2.1
Name: findimage
Version: 0.2.0
Summary: to find a template image(smaller) in a source image(bigger)
Home-page: https://github.com/songofhawk/findimage
Author: songofhawk
Author-email: songofhawk@gmail.com
License: MIT
Classifier: License :: OSI Approved :: MIT License
Classifier: Programming Language :: Python :: 3
Classifier: Operating System :: OS Independent
License-File: LICENSE
Requires-Dist: opencv-python (>=3.0)
